{"_default": {"1": {"date_save": "2023-10-31T14:00:15.894766", "name": "Round TROPHY", "numero_round": 1, "list_doc_id_matchs": [1]}, "2": {"date_save": "2023-10-31T14:00:22.713965", "name": "Round TROPHY", "numero_round": 2, "list_doc_id_matchs": [2]}, "3": {"date_save": "2023-10-31T14:00:33.122916", "name": "Round TROPHY", "numero_round": 3, "list_doc_id_matchs": [3]}, "4": {"date_save": "2023-10-31T14:02:56.939836", "name": "Round CHAMPIONNAT", "numero_round": 1, "list_doc_id_matchs": [4]}, "5": {"date_save": "2023-10-31T14:03:04.019861", "name": "Round CHAMPIONNAT", "numero_round": 2, "list_doc_id_matchs": [5]}, "6": {"date_save": "2023-10-31T14:03:30.770360", "name": "Round CHAMPIONNAT", "numero_round": 3, "list_doc_id_matchs": [6]}, "7": {"date_save": "2023-10-31T14:10:46.919106", "name": "Round TEST", "numero_round": 1, "list_doc_id_matchs": [7, 8]}, "8": {"date_save": "2023-10-31T14:11:39.842501", "name": "Round TEST", "numero_round": 2, "list_doc_id_matchs": [9, 10]}, "9": {"date_save": "2023-10-31T14:16:04.127010", "name": "Round FFF", "numero_round": 1, "list_doc_id_matchs": [11]}, "10": {"date_save": "2023-10-31T15:14:32.165618", "name": "Round ZAE", "numero_round": 1, "list_doc_id_matchs": [12]}, "11": {"date_save": "2023-10-31T15:14:35.232139", "name": "Round ZAE", "numero_round": 2, "list_doc_id_matchs": [13]}, "12": {"date_save": "2023-10-31T15:18:45.364101", "name": "Round AZEAZ", "numero_round": 1, "list_doc_id_matchs": [14]}, "13": {"date_save": "2023-10-31T15:18:58.564467", "name": "Round AZEAZ", "numero_round": 2, "list_doc_id_matchs": [15]}}}